scuffed_python_orchestrator/__init__.py
scuffed_python_orchestrator/app.py
scuffed_python_orchestrator/config_widget.py
scuffed_python_orchestrator/configure_process.py
scuffed_python_orchestrator/main_toolbar.py
scuffed_python_orchestrator/process_info.py
scuffed_python_orchestrator/process_manager.py
scuffed_python_orchestrator/py_process.py
scuffed_python_orchestrator/py_process_controller.py
scuffed_python_orchestrator/py_process_dashboard.py
scuffed_python_orchestrator/schedule_objects.py
scuffed_python_orchestrator/data/app.spec
scuffed_python_orchestrator/data/config.yaml
scuffed_python_orchestrator/data/icon.PNG
scuffed_python_orchestrator/data/icon.ico
scuffed_python_orchestrator-0.1.1.dist-info/METADATA
scuffed_python_orchestrator-0.1.1.dist-info/WHEEL
scuffed_python_orchestrator-0.1.1.dist-info/top_level.txt
scuffed_python_orchestrator-0.1.1.dist-info/RECORD
