Metadata-Version: 2.1
Name: scuffed_python_orchestrator
Version: 0.1.1
Summary: A semi-reliable orchestrator
Author: Michael Howard
Author-email: 
License: MIT
Classifier: License :: OSI Approved :: MIT License
Classifier: Programming Language :: Python :: 3.11
Classifier: Operating System :: OS Independent
Requires-Python: >=3.9
